jsw_bio/__init__.py
jsw_bio/base/__init__.py
jsw_bio/base/keyword.py
jsw_bio/base/url.py
jsw_bio/ncbi/__init__.py
jsw_bio/ncbi/entrez_download_accids.py
jsw_bio/ncbi/entrez_search_accids.py
jsw_bio/ncbi/ncbi_abstract_search.py
jsw_bio/ncbi/ncbi_download_accids.py
jsw_bio/ncbi/ncbi_fasta2md5.py
jsw_bio/ncbi/ncbi_fasta_text.py
jsw_bio/ncbi/ncbi_gb_parse.py
jsw_bio/ncbi/ncbi_gb_text.py
jsw_bio/ncbi/ncbi_search_ids.py
jsw_bio/ncbi/ncbi_search_ipg.py
jsw_bio/ncbi/ncbi_search_protein.py
jsw_bio/ncbi/ncbi_serialize_fasta.py
jsw_bio/ncbi/ncbi_sid.py
jsw_bio/ncbi/settings.py
jsw_bio-1.0.21.dist-info/WHEEL
jsw_bio-1.0.21.dist-info/METADATA
jsw_bio-1.0.21.dist-info/RECORD
