Metadata-Version: 2.1
Name: jsw-bio
Version: 1.0.21
Summary: Jsw for biography.
Home-page: https://js.work
Author: feizheng
Author-email: 1290657123@qq.com
Requires-Python: >=3.8,<4.0
Classifier: Programming Language :: Python :: 3
Classifier: Programming Language :: Python :: 3.10
Classifier: Programming Language :: Python :: 3.8
Classifier: Programming Language :: Python :: 3.9
Requires-Dist: biopython (>=1.79,<2.0)
Requires-Dist: bs4 (>=0.0.1,<0.0.2)
Requires-Dist: jsw-nx (>=1.0.104,<2.0.0)
Requires-Dist: nltk (>=3.7,<4.0)
Requires-Dist: numpy (>=1.22.4,<2.0.0)
Requires-Dist: psutil (>=5.9.0,<6.0.0)
Requires-Dist: requests (>=2.27.1,<3.0.0)
Project-URL: Repository, https://github.com/aric-pypi/jsw-bio
